{
 "actions": [],
 "autoname": "EXP-ATT-",
 "creation": "2021-02-03 14:36:16.856014",
 "doctype": "DocType",
 "editable_grid": 1,
 "engine": "InnoDB",
 "field_order": [
  "document_type",
  "document"
 ],
 "fields": [
  {
   "columns": 7,
   "fieldname": "document_type",
   "fieldtype": "Select",
   "in_list_view": 1,
   "label": "Document Type",
   "options": "--Select Document Type--\nID\nBusiness Registration Certificate\nBusiness Commencement Certificate\nFingerprint Impressions"
  },
  {
   "columns": 3,
   "fieldname": "document",
   "fieldtype": "Attach",
   "in_list_view": 1,
   "label": "Document"
  }
 ],
 "index_web_pages_for_search": 1,
 "istable": 1,
 "links": [],
 "modified": "2021-02-03 15:47:06.537839",
 "modified_by": "Administrator",
 "module": "Security Check Desk",
 "name": "Exporter Attachments",
 "owner": "Administrator",
 "permissions": [],
 "quick_entry": 1,
 "sort_field": "modified",
 "sort_order": "DESC",
 "track_changes": 1
}